myPyllant/__init__.py
myPyllant/api.py
myPyllant/const.py
myPyllant/enums.py
myPyllant/export.py
myPyllant/http_client.py
myPyllant/models.py
myPyllant/py.typed
myPyllant/report.py
myPyllant/sample.py
myPyllant/utils.py
myPyllant/tests/__init__.py
myPyllant/tests/conftest.py
myPyllant/tests/find_countries.py
myPyllant/tests/generate_test_data.py
myPyllant/tests/run_function_test.py
myPyllant/tests/test_api.py
myPyllant/tests/test_countries.py
myPyllant/tests/test_export.py
myPyllant/tests/test_generate_test_data.py
myPyllant/tests/test_models.py
myPyllant/tests/test_sample.py
myPyllant/tests/test_utils.py
myPyllant/tests/update_sample.py
myPyllant/tests/utils.py
myPyllant/tests/data/ambisense2.yaml
myPyllant/tests/data/no_cooling.yaml
myPyllant/tests/data/vrc700_dhw.yaml
myPyllant/tests/data/vrc700_mpc_rts.yaml
myPyllant/tests/data/vrc700_ventilation.yaml
myPyllant/tests/data/ambisense/homes.json
myPyllant/tests/data/ambisense/fc9ac9ea562b2a82a48708045a7c628e33c0de4b/connection_status.json
myPyllant/tests/data/ambisense/fc9ac9ea562b2a82a48708045a7c628e33c0de4b/control_identifier.json
myPyllant/tests/data/ambisense/fc9ac9ea562b2a82a48708045a7c628e33c0de4b/current_system.json
myPyllant/tests/data/ambisense/fc9ac9ea562b2a82a48708045a7c628e33c0de4b/diagnostic_trouble_codes.json
myPyllant/tests/data/ambisense/fc9ac9ea562b2a82a48708045a7c628e33c0de4b/mpc.json
myPyllant/tests/data/ambisense/fc9ac9ea562b2a82a48708045a7c628e33c0de4b/rbr.json
myPyllant/tests/data/ambisense/fc9ac9ea562b2a82a48708045a7c628e33c0de4b/rooms.json
myPyllant/tests/data/ambisense/fc9ac9ea562b2a82a48708045a7c628e33c0de4b/rts.json
myPyllant/tests/data/ambisense/fc9ac9ea562b2a82a48708045a7c628e33c0de4b/system.json
myPyllant/tests/data/ambisense/fc9ac9ea562b2a82a48708045a7c628e33c0de4b/time_zone.json
myPyllant/tests/data/current_power/homes.json
myPyllant/tests/data/current_power/4f5dff076e0dd0245aa0993a3d6f0e38754dd926/connection_status.json
mypyllant-0.9.9.dist-info/METADATA
mypyllant-0.9.9.dist-info/WHEEL
mypyllant-0.9.9.dist-info/licenses/LICENSE
mypyllant-0.9.9.dist-info/RECORD
